hkvportal/__init__.py
hkvportal/services.py
hkvportal/untangle.py
hkvportal-0.4.dist-info/LICENSE
hkvportal-0.4.dist-info/WHEEL
hkvportal-0.4.dist-info/METADATA
hkvportal-0.4.dist-info/RECORD
