Metadata-Version: 2.1
Name: hkvportal
Version: 0.4
Summary: hkvportal - module to access dataservices
Home-page: https://github.com/HKV-products-services/hkvportal
License: UNKNOWN
Author: Mattijn van Hoek
Author-email: hoek@hkv.nl
Classifier: License :: OSI Approved :: GNU General Public License v3 or later (GPLv3+)
